setup.py
electricity_bill.egg-info/PKG-INFO
electricity_bill.egg-info/SOURCES.txt
electricity_bill.egg-info/dependency_links.txt
electricity_bill.egg-info/not-zip-safe
electricity_bill.egg-info/top_level.txt
electricity_billing/__init__.py
electricity_billing/electricity_billing.py