Metadata-Version: 2.1
Name: electricity-bill
Version: 0.1
Summary: Electricity bill calculation for monthly domestic use
Author: ivankostark
